rulexai/__init__.py
rulexai/explainer.py
rulexai/importances.py
rulexai/models.py
rulexai/reduct.py
rulexai/rule.py
rulexai-1.1.0.dist-info/LICENSE
rulexai-1.1.0.dist-info/METADATA
rulexai-1.1.0.dist-info/WHEEL
rulexai-1.1.0.dist-info/top_level.txt
rulexai-1.1.0.dist-info/RECORD
