Metadata-Version: 2.1
Name: rulexai
Version: 1.1.0
Summary: RuleXAI is a rule-based aproach to explain the output of any machine learning model. It is suitable for classification, regression and survival tasks.
Home-page: https://github.com/adaa-polsl/RuleXAI
Author: Dawid Macha
Author-email: dawid.m.macha@gmail.com
Classifier: Development Status :: 5 - Production/Stable
Classifier: License :: OSI Approved :: GNU Affero General Public License v3
Classifier: Programming Language :: Python :: 3
Classifier: Operating System :: Microsoft :: Windows
Classifier: Operating System :: Unix
Classifier: Topic :: Scientific/Engineering
Classifier: Topic :: Scientific/Engineering :: Artificial Intelligence
Classifier: Intended Audience :: Developers
Classifier: Intended Audience :: Science/Research
Requires-Python: >=3.9
License-File: LICENSE
Requires-Dist: pandas <2.3.0,>=1.5.0
Requires-Dist: numpy ~=1.26.4
Requires-Dist: matplotlib ~=3.8.3
Requires-Dist: rulekit ~=1.7.6
Requires-Dist: lifelines ~=0.28.0
